[{
    "id": "1",
    "userId" : "1",
    "firstName" :"Dock",
    "lastName" : "Developers",
    "phoneNo" : "111111111",
    "profilePic" : "www.dockdevelopers.com/image1.jpg",
    "dateOfBirth": "11-11-1996",
    "address": "Lorem",
    "isMainAccount" : "0",
    "gender": "Male",
    "email" : "business@dockdevelopers.com",
    "isRaffleWinner" : "1",
    "flag" : "1",
    "createdBy": "DockDevelopers",
    "createdDate": "2011-06-14T04:12:36.123Z",
    "updatedBy": "DockDevelopers",
    "updatedDate": "2011-06-14T04:12:36.123Z",
    "blockedBy": "DockDevelopers",
    "blockedDate": "2011-06-14T04:12:36.123Z",
    "deletedBy": "DockDevelopers",
    "deletedDate": "2011-06-14T04:12:36.123Z"
},
    {
        
  
        "id": "2",
        "userId" : "2",
        "firstName" :"Dock",
        "lastName" : "Developers",
        "phoneNo" : "2222222",
        "profilePic" : "www.dockdevelopers.com/image2.jpg",
        "dateOfBirth": "11-11-1996",
        "address": "Lorem",
        "isMainAccount" : "0",
        "gender": "Male",
        "email" : "business@dockdevelopers.com",
        "isRaffleWinner" : "1",
        "flag" : "1",
        "createdBy": "DockDevelopers",
        "createdDate": "2011-06-14T04:12:36.123Z",
        "updatedBy": "DockDevelopers",
        "updatedDate": "2011-06-14T04:12:36.123Z",
        "blockedBy": "DockDevelopers",
        "blockedDate": "2011-06-14T04:12:36.123Z",
        "deletedBy": "DockDevelopers",
        "deletedDate": "2011-06-14T04:12:36.123Z"
    }
]